fancy_collections/__init__.py
fancy_collections/core.py
fancy_collections/formatting.py
fancy_collections/lib.py
fancy_collections-0.3.0.dist-info/LICENSE
fancy_collections-0.3.0.dist-info/METADATA
fancy_collections-0.3.0.dist-info/WHEEL
fancy_collections-0.3.0.dist-info/top_level.txt
fancy_collections-0.3.0.dist-info/RECORD
