Metadata-Version: 2.1
Name: fancy_collections
Version: 0.3.0
Summary: Some useful collection classes.
Author-email: Bert Palm <bert.palm.home@gmail.com>
Project-URL: Homepage, https://github.com/palmb/fancy-collections
Project-URL: Bug Tracker, https://github.com/palmb/fancy-collections/issues
Classifier: Programming Language :: Python :: 3
Classifier: License :: OSI Approved :: GNU General Public License v3 (GPLv3)
Classifier: Operating System :: OS Independent
Requires-Python: >=3.7
License-File: LICENSE
Requires-Dist: sliceable-dict >=0.4.1
Requires-Dist: pandas >1.0.0
Requires-Dist: numpy >1.0.0
Provides-Extra: tests
Requires-Dist: black ; extra == 'tests'
Requires-Dist: pytest ; extra == 'tests'
